<annotation>
	<folder>JPEGImages</folder>
	<filename>j16_051211_2155_xn_35n161w_018_12N.jpg</filename>
	<path>../JPEGImages/j16_051211_2155_xn_35n161w_018_12N.jpg</path>
	<source>
		<database>Unknown</database>
	</source>
	<size>
		<width>779</width>
		<height>778</height>
		<depth>1</depth>
	</size>
	<segmented>0</segmented>
	<object>
		<name>dust_devil</name>
		<pose>Unspecified</pose>
		<truncated>0</truncated>
		<difficult>0</difficult>
		<bndbox>
			<xmin>84</xmin>
			<ymin>11</ymin>
			<xmax>284</xmax>
			<ymax>103</ymax>
		</bndbox>
	</object>
</annotation>